sciex/__init__.py
sciex/check_status.py
sciex/components.py
sciex/functions.py
sciex/gather_results.py
sciex/generate_run_scripts.py
sciex/reorganize_trials.py
sciex/result_types.py
sciex/trial_runner.py
sciex/util.py
sciex-0.2.dist-info/METADATA
sciex-0.2.dist-info/WHEEL
sciex-0.2.dist-info/top_level.txt
sciex-0.2.dist-info/RECORD
