Metadata-Version: 2.1
Name: sciex
Version: 0.2
Summary: Framework for "scientific" experiments (Result organization; Experiment and Trial setup; Baseline Comparisons)
Home-page: UNKNOWN
Author: Kaiyu Zheng
Author-email: kaiyutony@gmail.com
License: UNKNOWN
Platform: UNKNOWN
Requires-Python: >3.6
Requires-Dist: pyyaml
Requires-Dist: numpy
